{
    "groups": [
        {
            "prefabName": "Food",
            "prefabLabel":"Food1",
            "count": 0,
            "position": {
                "xMin": -30, "xMax": -40,
                "yMin": 1, "yMax": 1,
                "zMin": 20, "zMax": 40
            },
            "rotationRange": {
                "x": 0, "y": 360, "z": 0
            },
            "scaleRange": {
                "xMin": 0.6, "xMax": 0.6,
                "yMin": 0.6, "yMax": 0.6,
                "zMin": 0.6, "zMax": 0.6
            }
        },
        {
            "prefabName": "Food",
            "prefabLabel":"Food2",
            "count": 0,
            "position": {
                "xMin": -35, "xMax": -30,
                "yMin": 1, "yMax": 1,
                "zMin": -35, "zMax": -30
            },
            "rotationRange": {
                "x": 0, "y": 360, "z": 0
            },
            "scaleRange": {
                "xMin": 0.6, "xMax": 0.6,
                "yMin": 0.6, "yMax": 0.6,
                "zMin": 0.6, "zMax": 0.6
            }
        },
        {
            "prefabName": "Food",
            "prefabLabel":"Food3",
            "count": 0,
            "position": {
                "xMin": -3, "xMax": -1,
                "yMin": 1, "yMax": 1,
                "zMin": -3, "zMax": -1
            },
            "rotationRange": {
                "x": 0, "y": 360, "z": 0
            },
            "scaleRange": {
                "xMin": 0.6, "xMax": 0.6,
                "yMin": 0.6, "yMax": 0.6,
                "zMin": 0.6, "zMax": 0.6
            }
        },
        {
            "prefabName": "Apple",
            "prefabLabel":"Apple1",
            "count": 3,
            "position": {
                "xMin": -30, "xMax": -40,
                "yMin": 1, "yMax": 1,
                "zMin": 20, "zMax": 40
            },
            "rotationRange": {
                "x": 0, "y": 0, "z": 0
            },
            "scaleRange": {
                "xMin": 7, "xMax": 7,
                "yMin": 7, "yMax": 7,
                "zMin": 7, "zMax": 7
            }
        },
        {
            "prefabName": "Apple",
            "prefabLabel":"Apple2",
            "count": 3,
            "position": {
                "xMin": -35, "xMax": -30,
                "yMin": 1, "yMax": 1,
                "zMin": -35, "zMax": -30
            },
            "rotationRange": {
                "x": 0, "y": 0, "z": 0
            },
            "scaleRange": {
                "xMin": 7, "xMax": 7,
                "yMin": 7, "yMax": 7,
                "zMin": 7, "zMax": 7
            }
        },
        {
            "prefabName": "Apple",
            "prefabLabel":"Apple3",
            "count": 3,
            "position": {
                "xMin": -3, "xMax": -1,
                "yMin": 1, "yMax": 1,
                "zMin": -3, "zMax": -1
            },
            "rotationRange": {
                "x": 0, "y": 0, "z": 0
            },
            "scaleRange": {
                "xMin": 7, "xMax": 7,
                "yMin": 7, "yMax": 7,
                "zMin": 7, "zMax": 7
            }
        },
        {
            "prefabName": "Water",
            "prefabLabel":"Water",
            "count": 0,
            "position": {
                "xMin": 20, "xMax": 40,
                "yMin": 1, "yMax": 1,
                "zMin": 20, "zMax": 40
            },
            "rotationRange": {
                "x": 0, "y": 0, "z": 0
            },
            "scaleRange": {
                "xMin": 0.6, "xMax": 0.6,
                "yMin": 0.6, "yMax": 0.6,
                "zMin": 0.6, "zMax": 0.6
            }
        },
        {
            "prefabName": "Pond",
            "prefabLabel":"Pond",
            "count": 1,
            "position": {
                "xMin": 30, "xMax": 33,
                "yMin": 1, "yMax": 1,
                "zMin": 30, "zMax": 33
            },
            "rotationRange": {
                "x": 0, "y": 0, "z": 0
            },
            "scaleRange": {
                "xMin": 1.9, "xMax": 1.9,
                "yMin": 1, "yMax": 1,
                "zMin": 1.7, "zMax": 1.7
            }
        }
    ]
}